[
    {
        "Name": "Number 8: Heraldic King Genom-Heritage",
        "Rarity": "Ultra Rare",
        "Category": [
            "Effect Monster",
            "Xyz Monster"
        ]
    },
    {
        "Name": "Number 69: Heraldry Crest",
        "Rarity": "Ultra Rare",
        "Category": [
            "Effect Monster",
            "Xyz Monster"
        ]
    },
    {
        "Name": "Advanced Heraldry Art",
        "Rarity": "Ultra Rare",
        "Category": [
            "Normal Spell Card",
            "Spell"
        ]
    },
    {
        "Name": "Rank-Up-Magic Argent Chaos Force",
        "Rarity": "Ultra Rare",
        "Category": [
            "Normal Spell Card",
            "Spell"
        ]
    },
    {
        "Name": "Norito the Moral Leader",
        "Rarity": "Super Rare",
        "Category": [
            "Effect Monster",
            "Xyz Monster"
        ]
    },
    {
        "Name": "Skypalace Gangaridai",
        "Rarity": "Super Rare",
        "Category": [
            "Effect Monster",
            "Xyz Monster"
        ]
    },
    {
        "Name": "CXyz Skypalace Babylon",
        "Rarity": "Super Rare",
        "Category": [
            "Effect Monster",
            "Xyz Monster"
        ]
    },
    {
        "Name": "Number C69: Heraldry Crest of Horror",
        "Rarity": "Super Rare",
        "Category": [
            "Effect Monster",
            "Xyz Monster"
        ]
    },
    {
        "Name": "Number 18: Heraldry Patriarch",
        "Rarity": "Super Rare",
        "Category": [
            "Effect Monster",
            "Xyz Monster"
        ]
    },
    {
        "Name": "Heraldic Beast Amphisbaena",
        "Rarity": "Super Rare",
        "Category": [
            "Effect Monster"
        ]
    },
    {
        "Name": "Charged-Up Heraldry",
        "Rarity": "Super Rare",
        "Category": [
            "Normal Spell Card",
            "Spell"
        ]
    },
    {
        "Name": "Marshalling Field",
        "Rarity": "Super Rare",
        "Category": [
            "Continuous Trap Card",
            "Trap"
        ]
    },
    {
        "Name": "Fairy Cheer Girl",
        "Rarity": "Rare",
        "Category": [
            "Effect Monster",
            "Xyz Monster"
        ]
    },
    {
        "Name": "Mechquipped Angineer",
        "Rarity": "Rare",
        "Category": [
            "Effect Monster",
            "Xyz Monster"
        ]
    },
    {
        "Name": "CXyz Mechquipped Djinn Angeneral",
        "Rarity": "Rare",
        "Category": [
            "Effect Monster",
            "Xyz Monster"
        ]
    },
    {
        "Name": "CXyz Simon the Great Moral Leader",
        "Rarity": "Rare",
        "Category": [
            "Effect Monster",
            "Xyz Monster"
        ]
    },
    {
        "Name": "Comics Hero King Arthur",
        "Rarity": "Rare",
        "Category": [
            "Effect Monster",
            "Xyz Monster"
        ]
    },
    {
        "Name": "CXyz Comics Hero Legend Arthur",
        "Rarity": "Rare",
        "Category": [
            "Effect Monster",
            "Xyz Monster"
        ]
    },
    {
        "Name": "Battlecruiser Dianthus",
        "Rarity": "Rare",
        "Category": [
            "Effect Monster",
            "Xyz Monster"
        ]
    },
    {
        "Name": "CXyz Battleship Cherry Blossom",
        "Rarity": "Rare",
        "Category": [
            "Effect Monster",
            "Xyz Monster"
        ]
    },
    {
        "Name": "Heraldic Beast Twin-Headed Eagle",
        "Rarity": "Rare",
        "Category": [
            "Effect Monster"
        ]
    },
    {
        "Name": "Heraldic Beast Leo",
        "Rarity": "Rare",
        "Category": [
            "Effect Monster"
        ]
    },
    {
        "Name": "Augmented Heraldry",
        "Rarity": "Rare",
        "Category": [
            "Field Spell Card",
            "Spell"
        ]
    },
    {
        "Name": "Resurgam Xyz",
        "Rarity": "Rare",
        "Category": [
            "Continuous Trap Card",
            "Trap"
        ]
    },
    {
        "Name": "Number 92: Heart-eartH Dragon",
        "Rarity": "Common",
        "Category": [
            "Effect Monster",
            "Xyz Monster"
        ]
    },
    {
        "Name": "Number 53: Heart-eartH",
        "Rarity": "Common",
        "Category": [
            "Effect Monster",
            "Xyz Monster"
        ]
    },
    {
        "Name": "Coach King Giantrainer",
        "Rarity": "Common",
        "Category": [
            "Effect Monster",
            "Xyz Monster"
        ]
    },
    {
        "Name": "CXyz Dark Fairy Cheer Girl",
        "Rarity": "Common",
        "Category": [
            "Effect Monster",
            "Xyz Monster"
        ]
    },
    {
        "Name": "CXyz Coach Lord Ultimatrainer",
        "Rarity": "Common",
        "Category": [
            "Effect Monster",
            "Xyz Monster"
        ]
    },
    {
        "Name": "Number C92: Heart-eartH Chaos Dragon",
        "Rarity": "Common",
        "Category": [
            "Effect Monster",
            "Xyz Monster"
        ]
    },
    {
        "Name": "Heraldic Beast Aberconway",
        "Rarity": "Common",
        "Category": [
            "Effect Monster"
        ]
    },
    {
        "Name": "Heraldic Beast Berners Falcon",
        "Rarity": "Common",
        "Category": [
            "Effect Monster"
        ]
    },
    {
        "Name": "Heraldic Beast Basilisk",
        "Rarity": "Common",
        "Category": [
            "Effect Monster"
        ]
    },
    {
        "Name": "Heraldic Beast Eale",
        "Rarity": "Common",
        "Category": [
            "Effect Monster"
        ]
    },
    {
        "Name": "Heraldic Beast Unicorn",
        "Rarity": "Common",
        "Category": [
            "Effect Monster"
        ]
    },
    {
        "Name": "Garbage Ogre",
        "Rarity": "Common",
        "Category": [
            "Effect Monster"
        ]
    },
    {
        "Name": "Garbage Lord",
        "Rarity": "Common",
        "Category": [
            "Effect Monster"
        ]
    },
    {
        "Name": "Heraldry Reborn",
        "Rarity": "Common",
        "Category": [
            "Normal Spell Card",
            "Spell"
        ]
    },
    {
        "Name": "Heraldry Change",
        "Rarity": "Common",
        "Category": [
            "Normal Trap Card",
            "Trap"
        ]
    },
    {
        "Name": "Heraldry Record",
        "Rarity": "Common",
        "Category": [
            "Counter Trap Card",
            "Trap"
        ]
    }
]