[
    {
        "Name": "Subterror Behemoth Fiendess",
        "Rarity": "Ultra Rare",
        "Category": [
            "Effect Monster",
            "Link Monster"
        ]
    },
    {
        "Name": "Jormungandr, Generaider Boss of Eternity",
        "Rarity": "Ultra Rare",
        "Category": [
            "Effect Monster",
            "Xyz Monster"
        ]
    },
    {
        "Name": "Subterror Guru",
        "Rarity": "Ultra Rare",
        "Category": [
            "Flip monster"
        ]
    },
    {
        "Name": "Mardel, Generaider Boss of Light",
        "Rarity": "Ultra Rare",
        "Category": [
            "Effect Monster"
        ]
    },
    {
        "Name": "Subterror Nemesis Warrior",
        "Rarity": "Super Rare",
        "Category": [
            "Effect Monster"
        ]
    },
    {
        "Name": "Subterror Behemoth Umastryx",
        "Rarity": "Super Rare",
        "Category": [
            "Flip monster"
        ]
    },
    {
        "Name": "Subterror Behemoth Stalagmo",
        "Rarity": "Super Rare",
        "Category": [
            "Flip monster"
        ]
    },
    {
        "Name": "Hela, Generaider Boss of Doom",
        "Rarity": "Super Rare",
        "Category": [
            "Effect Monster"
        ]
    },
    {
        "Name": "Harr, Generaider Boss of Storms",
        "Rarity": "Super Rare",
        "Category": [
            "Effect Monster"
        ]
    },
    {
        "Name": "Loptr, Shadow of the Generaider Bosses",
        "Rarity": "Super Rare",
        "Category": [
            "Effect Monster"
        ]
    },
    {
        "Name": "The Hidden City",
        "Rarity": "Super Rare",
        "Category": [
            "Field Spell Card",
            "Spell"
        ]
    },
    {
        "Name": "Generaider Boss Fight",
        "Rarity": "Super Rare",
        "Category": [
            "Normal Trap Card",
            "Trap"
        ]
    },
    {
        "Name": "Subterror Behemoth Ultramafus",
        "Rarity": "Rare",
        "Category": [
            "Flip monster"
        ]
    },
    {
        "Name": "Subterror Behemoth Speleogeist",
        "Rarity": "Rare",
        "Category": [
            "Flip monster"
        ]
    },
    {
        "Name": "Cataclysmic Scorching Sunburner",
        "Rarity": "Rare",
        "Category": [
            "Effect Monster"
        ]
    },
    {
        "Name": "Cataclysmic Cryonic Coldo",
        "Rarity": "Rare",
        "Category": [
            "Effect Monster"
        ]
    },
    {
        "Name": "Frodi, Generaider Boss of Swords",
        "Rarity": "Rare",
        "Category": [
            "Effect Monster"
        ]
    },
    {
        "Name": "Dovelgus, Generaider Boss of Iron",
        "Rarity": "Rare",
        "Category": [
            "Effect Monster"
        ]
    },
    {
        "Name": "Utgarda, Generaider Boss of Delusion",
        "Rarity": "Rare",
        "Category": [
            "Effect Monster"
        ]
    },
    {
        "Name": "Cataclysmic Crusted Calcifida",
        "Rarity": "Rare",
        "Category": [
            "Effect Monster"
        ]
    },
    {
        "Name": "Cataclysmic Circumpolar Chilblainia",
        "Rarity": "Rare",
        "Category": [
            "Effect Monster"
        ]
    },
    {
        "Name": "Generaider Boss Stage",
        "Rarity": "Rare",
        "Category": [
            "Field Spell Card",
            "Spell"
        ]
    },
    {
        "Name": "Subterror Final Battle",
        "Rarity": "Rare",
        "Category": [
            "Normal Trap Card",
            "Trap"
        ]
    },
    {
        "Name": "Subterror Succession",
        "Rarity": "Rare",
        "Category": [
            "Normal Trap Card",
            "Trap"
        ]
    },
    {
        "Name": "Subterror Nemesis Archer",
        "Rarity": "Common",
        "Category": [
            "Effect Monster"
        ]
    },
    {
        "Name": "Subterror Behemoth Stygokraken",
        "Rarity": "Common",
        "Category": [
            "Flip monster"
        ]
    },
    {
        "Name": "Subterror Nemesis Defender",
        "Rarity": "Common",
        "Category": [
            "Effect Monster"
        ]
    },
    {
        "Name": "Subterror Behemoth Dragossuary",
        "Rarity": "Common",
        "Category": [
            "Flip monster"
        ]
    },
    {
        "Name": "Subterror Behemoth Voltelluric",
        "Rarity": "Common",
        "Category": [
            "Flip monster"
        ]
    },
    {
        "Name": "Subterror Fiendess",
        "Rarity": "Common",
        "Category": [
            "Effect Monster"
        ]
    },
    {
        "Name": "Subterror Behemoth Phospheroglacier",
        "Rarity": "Common",
        "Category": [
            "Flip monster"
        ]
    },
    {
        "Name": "Naglfar, Generaider Boss of Fire",
        "Rarity": "Common",
        "Category": [
            "Effect Monster"
        ]
    },
    {
        "Name": "Nidhogg, Generaider Boss of Ice",
        "Rarity": "Common",
        "Category": [
            "Effect Monster"
        ]
    },
    {
        "Name": "Subterror Cave Clash",
        "Rarity": "Common",
        "Category": [
            "Continuous Spell Card",
            "Spell"
        ]
    },
    {
        "Name": "Generaider Boss Quest",
        "Rarity": "Common",
        "Category": [
            "Normal Spell Card",
            "Spell"
        ]
    },
    {
        "Name": "Generaider Boss Loot",
        "Rarity": "Common",
        "Category": [
            "Continuous Spell Card",
            "Spell"
        ]
    },
    {
        "Name": "Subterror Behemoth Burrowing",
        "Rarity": "Common",
        "Category": [
            "Normal Trap Card",
            "Trap"
        ]
    },
    {
        "Name": "Parthian Shot",
        "Rarity": "Common",
        "Category": [
            "Counter Trap Card",
            "Trap"
        ]
    },
    {
        "Name": "Generaider Boss Room",
        "Rarity": "Common",
        "Category": [
            "Continuous Trap Card",
            "Trap"
        ]
    },
    {
        "Name": "Generaider Boss Bite",
        "Rarity": "Common",
        "Category": [
            "Normal Trap Card",
            "Trap"
        ]
    }
]